llb_doc/__init__.py
llb_doc/cache/__init__.py
llb_doc/cache/cache.py
llb_doc/core/__init__.py
llb_doc/core/block.py
llb_doc/core/ctx.py
llb_doc/core/document.py
llb_doc/core/edge.py
llb_doc/core/graph_document.py
llb_doc/core/node.py
llb_doc/generators/__init__.py
llb_doc/generators/registry.py
llb_doc/parser/__init__.py
llb_doc/parser/parser.py
llb_doc/renderer/__init__.py
llb_doc/sorters/__init__.py
llb_doc/sorters/registry.py
llb_doc-0.3.0.dist-info/licenses/LICENSE
llb_doc-0.3.0.dist-info/METADATA
llb_doc-0.3.0.dist-info/WHEEL
llb_doc-0.3.0.dist-info/top_level.txt
llb_doc-0.3.0.dist-info/RECORD
