Metadata-Version: 2.4
Name: llb_doc
Version: 0.3.0
Summary: Large Language Blocks - A context packaging format for LLMs
Author-email: 4fuu <hi@4fwu.com>
License-Expression: MIT
Project-URL: Homepage, https://github.com/4fuu/llb
Project-URL: Repository, https://github.com/4fuu/llb
Requires-Python: >=3.9
License-File: LICENSE
Dynamic: license-file
